MANIFEST.in
README.rst
setup.py
docs/HISTORY.txt
docs/INSTALL.txt
docs/LICENSE.GPL
docs/LICENSE.txt
rt/__init__.py
rt.calendarinandout.egg-info/PKG-INFO
rt.calendarinandout.egg-info/SOURCES.txt
rt.calendarinandout.egg-info/dependency_links.txt
rt.calendarinandout.egg-info/entry_points.txt
rt.calendarinandout.egg-info/namespace_packages.txt
rt.calendarinandout.egg-info/not-zip-safe
rt.calendarinandout.egg-info/requires.txt
rt.calendarinandout.egg-info/top_level.txt
rt/calendarinandout/__init__.py
rt/calendarinandout/configure.zcml
rt/calendarinandout/widget.py
rt/calendarinandout/browser/__init__.py
rt/calendarinandout/browser/configure.zcml
rt/calendarinandout/browser/images/add_icon.gif
rt/calendarinandout/browser/images/delete_icon.gif
rt/calendarinandout/browser/images/popup_calendar.gif
rt/calendarinandout/profiles/default/metadata.xml
rt/calendarinandout/profiles/default/registry.xml
rt/calendarinandout/profiles/default/skins.xml
rt/calendarinandout/skins/rt_calendarinandout/jquery.ui.datepicker-it.js
rt/calendarinandout/skins/rt_calendarinandout/rt.calendarinandout.js
rt/calendarinandout/skins/rt_calendarinandout/rt_calendarinandout.pt