Metadata-Version: 1.1
Name: rt.calendarinandout
Version: 1.2.0
Summary: A LinesWidget-like for Plone, used for selecting dates
Home-page: http://plone.org/products/rt.calendarinandout
Author: RedTurtle Technology
Author-email: sviluppoplone@redturtle.it
License: GPL
Keywords: plone widget lines calendar jquery jquery-ui
Platform: UNKNOWN
Classifier: Framework :: Plone
Classifier: Framework :: Plone :: 4.0
Classifier: Framework :: Plone :: 4.1
Classifier: Framework :: Plone :: 4.2
Classifier: Framework :: Plone :: 4.3
Classifier: Programming Language :: Python
Classifier: Programming Language :: JavaScript
Classifier: Intended Audience :: Developers
Classifier: License :: OSI Approved :: GNU General Public License (GPL)
